llama_index/storage/kvstore/duckdb/__init__.py
llama_index/storage/kvstore/duckdb/base.py
llama_index_storage_kvstore_duckdb-0.2.1.dist-info/METADATA
llama_index_storage_kvstore_duckdb-0.2.1.dist-info/WHEEL
llama_index_storage_kvstore_duckdb-0.2.1.dist-info/licenses/LICENSE
llama_index_storage_kvstore_duckdb-0.2.1.dist-info/RECORD
