Metadata-Version: 2.4
Name: llama-index-storage-kvstore-duckdb
Version: 0.2.1
Summary: llama-index kvstore duckdb integration
Author-email: Your Name <you@example.com>
License-Expression: MIT
License-File: LICENSE
Requires-Python: <4.0,>=3.9
Requires-Dist: duckdb<1.4.0,>=0.10.1
Requires-Dist: llama-index-core<0.15,>=0.13.0
Requires-Dist: llama-index-vector-stores-duckdb>=0.4.2
Requires-Dist: pyarrow>=20.0.0
